{
  "title": "Auto Start User App",
  "x-stoplight": {
    "id": "3diq5g1c0zflf"
  },
  "type": "object",
  "description": "Enables/Disables the Auto start for User App",
  "properties": {
    "command": {
      "type": "string",
      "enum": [
        "autostart_user_app"
      ],
      "example": "autostart_user_app",
      "description": "The value for the key command must be autostart_user_app"
    },
    "command_id": {
      "type": "string",
      "example": "abcd1234",
      "description": "A unique ID that will be echoed back in the command response by the reader."
    },
    "payload": {
      "title": "set_autostartUserapp",
      "type": "object",
      "description": "configure auto start settings for userapp",
      "properties": {
        "appname": {
          "type": "string",
          "description": "Application name. For REST, the application is identified by the appname path parameter; for MQTT, the application is identified by the appname payload field.",
          "example": "userapp name"
        },
        "autostart": {
          "type": "boolean",
          "default": true,
          "description": "Whether the application should start automatically when the reader starts."
        }
      },
      "required": [
        "appname",
        "autostart"
      ]
    }
  },
  "required": [
    "command",
    "command_id",
    "payload"
  ]
}
